{
  "id": "a0464a743d2143c28537ea64b2cc384e",
  "type": "view",
  "channel": "Quebecor",
  "title": "Rattrapege tele",
  "relationships": {
    "collections": {
      "data": [
        {
          "id": "featured-items",
          "type": "collection"
        },
        {
          "id": "featured-items",
          "type": "collection"
        },
        {
          "id": "featured-items",
          "type": "collection"
        },
        {
          "id": "featured-items",
          "type": "collection"
        }
      ]
    }
  }
}
